django_elasticsearch_dsl/__init__.py
django_elasticsearch_dsl/apps.py
django_elasticsearch_dsl/documents.py
django_elasticsearch_dsl/exceptions.py
django_elasticsearch_dsl/fields.py
django_elasticsearch_dsl/indices.py
django_elasticsearch_dsl/models.py
django_elasticsearch_dsl/registries.py
django_elasticsearch_dsl/search.py
django_elasticsearch_dsl/signals.py
django_elasticsearch_dsl/management/__init__.py
django_elasticsearch_dsl/management/commands/__init__.py
django_elasticsearch_dsl/management/commands/search_index.py
django_elasticsearch_dsl/test/__init__.py
django_elasticsearch_dsl/test/testcases.py
lc_django_elasticsearch_dsl-7.1.3.dist-info/AUTHORS.rst
lc_django_elasticsearch_dsl-7.1.3.dist-info/LICENSE
lc_django_elasticsearch_dsl-7.1.3.dist-info/METADATA
lc_django_elasticsearch_dsl-7.1.3.dist-info/WHEEL
lc_django_elasticsearch_dsl-7.1.3.dist-info/top_level.txt
lc_django_elasticsearch_dsl-7.1.3.dist-info/RECORD
