Metadata-Version: 2.1
Name: lc-django-elasticsearch-dsl
Version: 7.1.3
Summary: Wrapper around elasticsearch-dsl-py for django models
Home-page: https://github.com/sabricot/django-elasticsearch-dsl
Author: Sabricot
Author-email: UNKNOWN
License: Apache Software License 2.0
Keywords: django elasticsearch elasticsearch-dsl
Platform: UNKNOWN
Classifier: Development Status :: 3 - Alpha
Classifier: Framework :: Django
Classifier: Framework :: Django :: 1.11
Classifier: Framework :: Django :: 2.0
Classifier: Framework :: Django :: 2.1
Classifier: Framework :: Django :: 2.2
Classifier: Framework :: Django :: 3.0
Classifier: Intended Audience :: Developers
Classifier: License :: OSI Approved :: BSD License
Classifier: Natural Language :: English
Classifier: Programming Language :: Python :: 2
Classifier: Programming Language :: Python :: 2.7
Classifier: Programming Language :: Python :: 3
Classifier: Programming Language :: Python :: 3.5
Classifier: Programming Language :: Python :: 3.6
Classifier: Programming Language :: Python :: 3.7
Classifier: Programming Language :: Python :: 3.8
Requires-Dist: elasticsearch-dsl (>=7.0.0<8.0.0)
Requires-Dist: six
